mozo/__init__.py
mozo/__main__.py
mozo/cli.py
mozo/factory.py
mozo/manager.py
mozo/registry.py
mozo/server.py
mozo/adapters/__init__.py
mozo/adapters/depth_anything.py
mozo/adapters/detectron2.py
mozo/adapters/qwen2_5_vl.py
mozo-0.2.0.dist-info/licenses/LICENSE
mozo-0.2.0.dist-info/METADATA
mozo-0.2.0.dist-info/WHEEL
mozo-0.2.0.dist-info/entry_points.txt
mozo-0.2.0.dist-info/top_level.txt
mozo-0.2.0.dist-info/RECORD
