Metadata-Version: 2.4
Name: mozo
Version: 0.2.0
Summary: Universal computer vision model serving library with dynamic model management and PixelFlow integration
Home-page: https://github.com/datamarkin/mozo
Author: Emrah NAZIF
Author-email: Emrah NAZIF <emrah@datamarkin.com>, Datamarkin <support@datamarkin.com>
License: MIT
Project-URL: Homepage, https://github.com/datamarkin/mozo
Project-URL: Bug Tracker, https://github.com/datamarkin/mozo/issues
Classifier: Development Status :: 3 - Alpha
Classifier: Intended Audience :: Developers
Classifier: License :: OSI Approved :: MIT License
Classifier: Programming Language :: Python :: 3
Classifier: Programming Language :: Python :: 3.9
Classifier: Programming Language :: Python :: 3.10
Classifier: Programming Language :: Python :: 3.11
Classifier: Programming Language :: Python :: 3.12
Requires-Python: >=3.9
License-File: LICENSE
Requires-Dist: fastapi
Requires-Dist: uvicorn
Requires-Dist: requests
Requires-Dist: opencv-python
Requires-Dist: transformers
Requires-Dist: torch
Requires-Dist: torchvision
Requires-Dist: Pillow
Requires-Dist: numpy
Requires-Dist: scipy
Requires-Dist: pixelflow
Requires-Dist: click
Dynamic: author
Dynamic: home-page
Dynamic: license-file
Dynamic: requires-python
